{"Lorukumo":["Domoye","Losimit","Napao"],"Lotaruk":["Lokitella","Nacheele","Nasinyonoit A","Trading Centre East","Naaoi","Trading Centre West","Natamaniyat"],"Nakuri":["Ajokolup","Lousugu","Ngurakadong","Lopeduru-Adengel"],"Sakale":["Lopeduru","Nangaamit","Nasinyonoit C","Namorulem","Okutot","Lokitela-Angikoria"],"Kamaturu":["Lokwakwa","Lorukumo","Naapong"],"Narisae":["Lokwamor","Nangaamit","Naaoi"],"Lorengedwat":["Nathinyonoit","Lonangat","Longoleyek","Naweet"],"Acegeretolim":["Cucu","Loteede A"],"Lokaala":["Nakudep","Napayan","Nathinyonoit","Lookom A"],"Moruangibuin":["Kaalakeju","Moruakimat","Nabilatuk Trading Centre","Moruangibuin","Ongora"],"Nakobekobe":["Nakobekobe","Napongae South","Namidi-Ka-Ao","Natapar-Arengan"],"Natapar-Arengan":["Natapar-Arengan","Nabwal","Loogitha","Lousugu","Magoro","Napwok"],"Natopojo":["Lonangat 'A'","Loojor 'A'"],"Nabilatuk":["Natopojo","Louta"],"Natirae":["Louta","Natirae","Kaloye"],"Namerisiya":["Lokibui","Nakurobuin","Nasinyonoit B"],"Korinyang":["Nakaala","Naligoi","Napuna"],"Moru-Angamion":["Moruangamion","Kalukalet","Nakaliye"],"Angaro":["Nakodiokodioi","Amagalimojong","Ariwokale","Kaanangakinoi"],"Kalokwameri":["Kalokwameri","Losimit","Napayan","Napongae","Alemukere","Lonyangatur","Napao"],"Kosike":["Kalokwameri","Kathiapus","Lopie"],"Kothike":["Longaroi","Natengerebet","Nayonai-Angikalio","Nasulut"],"Nakayot":["Kochomin","Lokitereng","Nakayot","Namonialoris","Morulem"],"Natopojo Ward":["Lokirimo","Lonangat B","Loojor B","Lookom B"],"Arengesiep Ward":["Ajijim","Arengesiep","Loteede B","Naachuka","Nayoroit"],"Central Ward":["Campswahili","Lodisi","Namerireng","Old Town"],"Lolet Ward":["Ariamaoi","Katanga"],"Nabilatuk Town Council":["Lolet Ward","Lolet","Nawokotelei"],"Naupala Ward":["Arecheck","Naupala","Lokorete","Nakerokandeke"]}