{"Akalale":["Adipala","Kalukumeri","Lobooko","Kocholut","Nakapelimen","Nakiceleet"],"Namugit":["Kanangar","Loligoi","Nakwamoru","Namugit","Lokimuko","Lokopo T.C","Lopana","Lokopo T.C West"],"Longalom":["Arengemunyen","Kokorio","Lokarujak","Lokiloli","Longalom","Loteede"],"Lorikitae":["Kalochonga","Lojojora","Lokoit","Lolemuyek","Lolita","Lopeta","Lorikitae","Loboborio"],"Lokopo":["Kayepas","Kachodo","Kayepas","Napeilet","Naputhiligoi","Loporokori"],"Lokudumo":["Kalesa","Loitakwa","Lomusia","Lopeduru","Lotaba","Lotop","Lotutua","Naoyakorete","Napetet","Nangoro","Naoyakaramwae"],"Lopeei":["Arengepuwa","Logolosimit","Lotede","Nakumae","Nariamaregae","Kacurokweei","Lokarukoi","Lopeei T.C","Nakatiyat"],"Nakwamoru":["Akarwon"],"Lopeei (2)":["Nakwamoru","Kailikong","Loodoi","Lokore","Lolewa","Lomaul","Lomuria","Loparipar","Lorengelup","Lorunget","Louta - Lokarukoi","Loutakou","Naregae","Lokapangiteng","Losonyoka","Naoi"],"Lokali":["Logurukocho","Lokitelakeemun","Lopopongo","Lorupayo","Morualoyete","Nangatunyo"],"Lokupoi":["Chelele","Kokorio","Lokupoi T.C","Lomariamong","Lorengekungin A"],"Matany":["Lokupoi","Lorengekungin B","Moruongor","Nakoelelei","Naligoi","Namoruongora","Lokitela","Namoru","Ongora"],"Lokuwas":["Kalapajak","Kooriaba","Nakanikan","Nasiloit","Lorukumo"],"Morulinga":["Kogete","Naacuka","Namukure","Naro - Apalotiyaro","Naro-Kokweta","Nasinyonoit"],"Nakicumet":["Kanaura","Kokeris","Losidongoror"],"Apeitolim":["Apeitolim T.C East","Giritome","Apeitolim T.C West","Katubakuyon"],"Apeitolim (2)":["Apeitolim","Locoae","Lomookori","Nabata","Kasile","Lokere","Namoru Akwangan","Achukudu","Achukudu","Agesai","Ajanit","Ajeleik","Akoboi","Ariamet","Atiling","Atirwae","Kanan","Liling","Odukojeni North","Odukojeni South","Jerusalem","Arengepuwa","Adipala","Akao Alosigiria","Akobokobot","Akol Muya","Akworo","Alungar","Aminit","Aolio","Apeduru"],"Apeitolim (3)":["Arengepuwa","Aputon","Arengepuwa","Asuruga","Aturwae","Odol Owany","Kaiungatuk","Arechek","Kacalakeny","Kaiungatuk","Lokwakais","Longaro","Nakoreto Corner","Nakouetom","Naparot","Kobulin","Ka-Akorinyang","Kobulin","Kocolo","Kotirwae","Lokito Kokeny Camp","Nakwakwa","Narengekitoe","Amaler","Apeduru","Kalowakemer","Karimakwee","Lokitela Angabukui","Loolimo","Nabelat","Nakwakwa Corner","Narengekitoe"],"Apeitolim (4)":["Narengekitoe","Turutuko","Lomokori","Albino","Amerekek","Apeduru","Locoae","Lokok","Lomokori","Naguleka"],"Kaeselem":["Kaethelem A","Kaethelem B","Konukunukia","Lokitela Kewapet","Losagari","Komuturunyo","Kapedaupal","Komuturunyo","Lokamita East","Lokamita West","Lokodet","Longaro","Loobore","Poron","Kabichurwa","Napao","Nariketakuma","Poron","Koputurio"],"Apungure Ward":["Lokitela Angakile","Lomuria Angakile","Dartics Ward","Abbatoir","Akuma","Kotipe","Senior Quarters","Boma","Cambi","Dhos","Police"],"Kololo Ward":["Kololo","Logolei","Lolain","Matany East Ward","Locholi","Lokwakais","Naarakorio","Matany T.C East","Matany West Ward","Down Town","Matany T.C West","Napeipelu Ward","Arionomunyen","Kaped Akuj","Looi","Kongkwa","Napeipelu"],"Iriiri":["Ariamakot","Iriiri Trading Centre","Kaurikiakine","Lomaratoit","Nabokat","Alekilek","Go Down","Kalopidinga","Kasile","Lobulio","Loyep Camp","Toyep Toto","Moru Sapir"],"Tepeth":["Kadacar","Lobulepeded","Lojom","Losikait","Nakisilet","Lokwanamoru","Naminit","Naturumrum","Akore","Alakas Camp","Lolet","Nakayot Camp","Namendera","Atumchoke","Kalopidinga","Kayodo"],"Iriiri (2)":["Namendera","Kongor-Yese","Namendera","Nabokat","Nakuyon"],"Kalokengel East":["Akwapua Loluk","Koititi","Nachuka","Angarab"],"Lomuno":["Lolet Bita","Lopuu","Nakaramwae","Adwaramukuny","Naoyaminit","Natapar Apalem"],"Moruongor":["Loolim","Naitakosowan","Angaro","Naronit","Kaingolejek","Naooi"],"Nariamaregae":["Lolet","Longaroi","Nakaale"],"Kalokengel West":["Lobeei","Loroo","Naitakwae"],"Lotome":["Kalokengel West","Naregae","Lominit","Nakorete"],"Kautakou":["Lotikokin","Nataari"],"Naitakwae":["Kakutalem","Naregae","Karuko","Lokodiokodioi","Lomaliga","Lowatakau","Naro Ongor"],"Narengemoru":["Ajokomoliteny","Lobur-Apaese"],"Nawaikorot":["Lomerimong","Nawaikorot A","Konyanga","Longariama","Loolimo","Too Ekitela"],"Nagule-Angolol":["Naguleangolol","Nakipomia"],"Lolet":["Kalokuruk","Kanaitakomol"],"Lorengecora":["Lolet","Lomoruchubae","Lomuriangalepan","Lokeru","Cholichol","Koomo","Cholichol","Lokupoi","Lomasenik","Nawatom","Kokipurat","Kocito","Kokikpurat","Lobok","Nakwakwa","Rapada"],"Kopopwa B Ward":["Lokitela","Nakumai"],"Lorengecora B":["Kobulin","Lorikitae","Lokeru","Lopapae","Namorulem"],"Kopopwa A Ward":["Lorengecora Tc","Lopiida","Kopopwa","Lorengecora A","Campswahili","Katanga","Lolet T.C"],"Nabwal":["Kaarid Ewapeto","Loputhak","Namorotot","Nabwal Camp","Nacoria","Amedek","Arengepuwa","Lokitela Angibulio","Nakaramwae","Lokacikit","Naloret","Napiananya","Michoko","Duol","Duol","Akucho","Aputiput","Kapadakook","Koperiperit","Koitu","Nathinyonoit","Kodike","Kokuwam","Kodike","Naabore","Nataparapalem","Makok","Naminit","Alica","Namenuain"],"Nabwal (2)":["Naminit","Naturobinya","Ariamiriam Camp","Naminit"],"Complex Ward":["Kangole B","Kangole G","Mission","Lopida Ward","Police","Lopiida A","Kangole Chin","Kangole Middle","Lopiida B","Nasike Ward","Lopeeny","Nasike","Nasike North","Senior Quarters","Loputuk","Nawaikorot B","Naligoi","Senior Quarters","Nawokotelei"]}