{"Kabete Ward":["Ndekye Ii","Ryeru Ii","Ryeru Iii"],"Kasarara Ward":["Kasarara I","Nyakasharu Ii","Kasungu","Rubirizi"],"Ndekye Ward":["Ndekye Iii","Kikuba","Ryeru I"],"Nyakasharu Ward":["Buhera Central","Nyakasharu I","Kyakabunda","Rugazi"],"Kashaka":["Kimanvu I","Kimanvu Ii","Nsingera I","Nsingera Ii"],"Katunguru":["Kigabo","Kyangabukama"],"Kazinga":["Kagera","Kanombe"],"Kishenyi":["Karambi","Nyamweru"],"Kichwamba":["Kyambuzi A","Kyambuzi B","Kyansama A","Kyansama B","Mirambi A","Mirambi B","Nyabubaare I"],"Rumuri":["Buhingo I","Buhingo Ii","Buhingo Iii","Kyankwanzi","Kyaruganda I","Kyaruganda Ii","Nyaruharo I","Nyaruharo Ii","Rumuri I","Rumuri Ii","Rwandaro I","Rwandaro Ii"],"Kataara":["Kyanyonza","Kataara I","Kataara Ii","Kataara Iii","Kyarutakoba I","Kyarutakoba Ii"],"Kyambura":["Kyambura C","Kagando A","Kagando B"],"Kichwamba (2)":["Kyambura","Kyambura A","Kyambura B","Omumasaka A","Omumasaka B","Nyakasozi","Busonga Ia","Busonga Ib","Busonga Ii A","Busonga Ii B","Nyabubare Ii B","Nyabubare Ii A","Nyakasozi A","Nyakasozi B"],"Buzenga":["Buzenga I","Buzenga Ii","Kamacumu I","Kamacumu Ii","Kabirizi I","Kabirizi Ii","Kyeibumba I","Kyeibumba Ii"],"Mushumba":["Birehe","Busingo","Buteezi","Nyakakaaka B","Rugyenda"],"Ndekye":["Kasoga"],"Ryeru":["Ndekye","Ndekye I","Nyakakaaka"],"Nyakiyanja":["Nkondo A","Nkondo B","Nyakiyanja A","Nyakiyanja B","Nyakiyanja C","Mubanda","Mubanda A","Mubanda B","Mubanda C","Mubanda D","Nyakakaaka A","Mugogo","Mugogo I","Mugogo Ii","Mugogo Iii","Nyamishekye","Ndangara","Kabukwiri","Karagara","Ndangara A","Ndangara B"],"Butoha":["Busonga","Butoha I","Butoha Ii","Kanyara","Nyakihanda","Nyangorogoro I"],"Magambo":["Butoha","Nyangorogoro Ii"],"Magambo (2)":["Kyabikonko","Njuguto","Nyakahaama","Ryekibagane I","Ryekibagane Ii"],"Rugazi":["Kyambogo","Nyakatunga","Nyakeiga"],"Bugaya":["Bugaya I","Bugaya Ii","Busonga Ii","Kigabiro","Kyeema","Rukiizi","Rubirizi","Kasarara Ii","Kijurugo"],"Ndangaro":["Kanyambiriri I","Kantungu","Kyanika I","Kyanika Ii","Nkombe I","Nkombe Ii"],"Nyabubare":["Birehe I","Bukyaba","Kyanika"],"Rutoto":["Nyabubare","Rwentuha","Birehe Ii"],"Bururuma":["Bururuma","Kagyezi","Rurama","Ryemondo"],"Kashenyi":["Kinoko B","Kanyambiriri Ii","Kashenyi","Kinoko A","Rwemitagu","Kyamabare","Nyabwina","Rwemitagu","Rwenkobe"],"Katerera":["Katonya","Mbuga A","Nyakahita","Nyamirima I A","Nyamirima Ii","Nyamirima Iii","Rukoma","Mbuga B","Nyamirima I B"],"Mwongyera":["Ibamba","Kidubule","Kagorogoro I","Kagorogoro Ii","Kagorogoro Iii","Mwongera I","Mwongera Ii","Kabashekye","Kemengo","Kirembe","Nyamabare","Kanyungu","Wandegeya","Kanyegaramire","Nyamabare I","Nyamabare Ii","Rwentojo Ii","Rwentojo Iii","Nyamirima","Nyabushabe","Nyamirima Iii"],"Katerera (2)":["Nyamirima","Nyamirima I","Nyamirima Ii"],"Mugyera":["Kisiita B","Kanyanshande A","Ryamatumba Iii","Kisiita A","Nyakatunga I","Nyakatunga Ii","Kanyanshande B"],"Katanda":["Kakindo C","Kanyantanga","Katanda I","Katanda Ii","Nyangorogoro A","Kakindo A","Kakindo B","Katakondwa","Katanda Iii","Nyangorogoro B"],"Munyonyi":["Mikonebiri I","Munyonyi I","Munyonyi Ii A","Munyonyi V","Mikonebiri Ii","Munyonyi Ii B"],"Kyankaranga":["Kikoma Ii"],"Katanda (2)":["Kyankaranga","Katokori I","Katokori Ii","Kikoma I","Kyankaranga I","Kyankaranga Ii","Kyankaranga Iii","Nyandongo","Kanjenje","Nyandongo I B","Nyandongo Iii","Munyonyi Iii","Munyonyi Iv","Nyandongo I A","Nyandongo Ii","Ryamatumba","Kisharu Ii","Ryamatumba Ii B","Kisharu I","Ryamatumba I A","Ryamatumba Ii A","Ryamatumba I B"],"Kakaari":["Igomanda I A","Kakaari I A","Kakaari Ii A","Nyakanengo","Nyakarambi I","Nyaruhanga","Igomanda I B"],"Kyabakara":["Kakaari","Kakaari I B","Kakaari Ii B","Nyakarambi Ii"],"Kyabakara (2)":["Kyenjojo Ii","Rwemiceeka","Kagando","Katabago I","Katabago Ii","Kyenjojo I","Ngoro","Butaturwa","Igomanda Ii A","Igomanda Iii","Ngoro I A","Ngoro Ii","Igomanda Ii B","Kasibo","Ngoro I B","Nyabubare","Katehe","Kinoni","Nyabubare Ii","Nyakagyera","Nyemeka","Mugombwa","Rutondo","Kagarama","Nyabubare I","Rugarama","Bwegiragye","Kalembo"],"Kyabakara (3)":["Rugarama","Nyamirama","Rugarama I","Rugarama Ii","Rusoro"],"Kacu Ward":["Kacu","Kizira","Kyamwiga","Muyenga Ward","Kacuba I","Kacuba Ii","Rwentojo I","Nyakagyezi Ward","Kaguga","Myonyo","Nyakagyezi I","Nyakagyezi Ii","Katerera Ward","Kabaseeke","Katerera I","Katerera Ii","Kikonjo"],"Kirugu":["Kafuro Ia","Kafuro Ib","Kafuro Ii","Kirugu I A"],"Kikumbo":["Kaberengye A","Kikumbo A"],"Kirugu (2)":["Kikumbo","Kirugu Ii A","Kyeizogombe","Ntunga A","Ntunga B","Omukabaare A","Kikumbo B","Kaberengye B","Kirugu Iib","Omukabaare B","Kyenzaza","Kirugu I B","Kyenzaza Ia","Kyenzaza Ib","Kyenzaza Ii A","Kyenzaza Ii B","Mirarikye","Mirarikye A","Mirarikye B","Mirarikye C"]}